[
    {
        "id": "Opsmx.CustomStagePlugin",
        "description": "An example of a PF4J-based plugin that provides a custom pipeline stage.",
        "provider": "https://github.com/opsmx",
        "releases": [
            {
                "version": "1.0.1",
                "date": "2024-04-05T08:18:46.747575Z",
                "requires": "orca>=0.0.0",
                "sha512sum": "c509646ebc82ce44edb342c47b71ab32bf6f3d52f8f24b783c32692d50fa00af81974b4304ae3cb0fb297cf456c868cc564909b85e78e9e6cc8983832c8d0cdd",
                "url": "https://raw.githubusercontent.com/opsmx-public/newspinplugin/main/pf4jCustomStagePlugin-v1.0.10.dirty-SNAPSHOT.zip"
            }
        ]
    }
]
